[{"sender_name":"Bilal Hasson","timestamp_ms":1607379446404,"content":"😂","type":"Generic","is_unsent":false},{"sender_name":"Bilal Hasson","timestamp_ms":1607379444221,"content":"Okay haha","type":"Generic","is_unsent":false},{"sender_name":"Bilal Hasson","timestamp_ms":1607379439191,"content":"Yeah of course","type":"Generic","is_unsent":false},{"sender_name":"Genevieve Hasson","timestamp_ms":1607379436839,"content":"No 🤷🏻‍♀️","type":"Generic","is_unsent":false},{"sender_name":"Genevieve Hasson","timestamp_ms":1607379421102,"content":"I’m going to try and rest for like15 min and. If I can’t can I call you,","type":"Generic","is_unsent":false},{"sender_name":"Bilal Hasson","timestamp_ms":1607379399900,"type":"Generic","is_unsent":false},{"sender_name":"Bilal Hasson","timestamp_ms":1607379342393,"content":"🤦🏽‍♂️","type":"Generic","is_unsent":false},{"sender_name":"Bilal Hasson","timestamp_ms":1607379339835,"content":"Your brain is so active!","type":"Generic","is_unsent":false},{"sender_name":"Bilal Hasson","timestamp_ms":1607379333477,"content":"My poor baby","type":"Generic","is_unsent":false},{"sender_name":"Bilal Hasson","timestamp_ms":1607379330162,"content":"Babbyyyy","type":"Generic","is_unsent":false},{"sender_name":"Genevieve Hasson","timestamp_ms":1607379179818,"content":"Baby baby baby","type":"Generic","is_unsent":false},{"sender_name":"Genevieve Hasson","timestamp_ms":1607379147942,"content":"My brain won’t shut off","type":"Generic","is_unsent":false},{"sender_name":"Genevieve Hasson","timestamp_ms":1607379136692,"content":"I’m so tired and trying to sleep but all I can think about is you🤷🏻‍♀️","type":"Generic","is_unsent":false},{"sender_name":"Genevieve Hasson","timestamp_ms":1607379112097,"content":"I love you","type":"Generic","is_unsent":false},{"sender_name":"Genevieve Hasson","timestamp_ms":1607379106166,"content":"I miss you","type":"Generic","is_unsent":false},{"sender_name":"Bilal Hasson","timestamp_ms":1607377330403,"share":{"link":"https://www.instagram.com/p/CIgdzcWAfrf/","share_text":"Double Tap/Drop a COMMENT!❤️😉 \nFollow @relationshiptales \nFollow @relationshiptales","original_content_owner":"relationshiptales"},"type":"Share","is_unsent":false},{"sender_name":"Genevieve Hasson","timestamp_ms":1607375513446,"content":"Hi!","type":"Generic","is_unsent":false},{"sender_name":"Bilal Hasson","timestamp_ms":1607374112167,"content":"How’s your meeting?","type":"Generic","is_unsent":false},{"sender_name":"Bilal Hasson","timestamp_ms":1607374094934,"content":"I’ve been needing it all afternoon!/evening 🥰","type":"Generic","is_unsent":false},{"sender_name":"Bilal Hasson","timestamp_ms":1607374083054,"content":"I can’t wait to bear your voice baby","type":"Generic","is_unsent":false},{"sender_name":"Bilal Hasson","timestamp_ms":1607374073540,"content":"👅","type":"Generic","is_unsent":false},{"sender_name":"Bilal Hasson","timestamp_ms":1607374067112,"content":"Your most grateful client 😏","type":"Generic","is_unsent":false},{"sender_name":"Bilal Hasson","timestamp_ms":1607374041636,"content":"I’m your client","type":"Generic","is_unsent":false},{"sender_name":"Bilal Hasson","timestamp_ms":1607374034799,"content":"Nooooooo","type":"Generic","is_unsent":false},{"sender_name":"Genevieve Hasson","timestamp_ms":1607373851132,"content":"Meeting!","type":"Generic","is_unsent":false},{"sender_name":"Bilal Hasson","timestamp_ms":1607371800530,"photos":"/genevieve/photos/130219945_1349572635388951_597137775129206415_n_683131039071289.jpg","type":"Generic","is_unsent":false},{"sender_name":"Bilal Hasson","timestamp_ms":1607371766014,"content":"I need youuuu","type":"Generic","is_unsent":false},{"sender_name":"Bilal Hasson","timestamp_ms":1607371700099,"content":"I miss you so much!","type":"Generic","is_unsent":false},{"sender_name":"Bilal Hasson","timestamp_ms":1607371699784,"content":"Babbbyy","type":"Generic","is_unsent":false},{"sender_name":"Bilal Hasson","timestamp_ms":1607371698885,"content":"Abbbyyyy","type":"Generic","is_unsent":false},{"sender_name":"Bilal Hasson","timestamp_ms":1607368578380,"content":"Hey baby, how’s your afternoon going?","type":"Generic","is_unsent":false},{"sender_name":"Bilal Hasson","timestamp_ms":1607368566698,"content":"I fucking love you!","type":"Generic","is_unsent":false},{"sender_name":"Bilal Hasson","timestamp_ms":1607364385684,"content":"I will always create it! 😏","type":"Generic","is_unsent":false},{"sender_name":"Bilal Hasson","timestamp_ms":1607364371513,"content":"Babbyyyy","type":"Generic","is_unsent":false},{"sender_name":"Bilal Hasson","timestamp_ms":1607364369545,"content":"Ugh!","type":"Generic","is_unsent":false},{"sender_name":"Genevieve Hasson","timestamp_ms":1607364094342,"content":"Just saying","type":"Generic","is_unsent":false},{"sender_name":"Genevieve Hasson","timestamp_ms":1607364089912,"content":"I need you to create my orgasm","type":"Generic","is_unsent":false},{"sender_name":"Genevieve Hasson","timestamp_ms":1607364074620,"content":"Reacted ❤️ to your message","type":"Generic","is_unsent":false},{"sender_name":"Genevieve Hasson","timestamp_ms":1607364073815,"content":"Reacted ❤️ to your message","type":"Generic","is_unsent":false},{"sender_name":"Genevieve Hasson","timestamp_ms":1607364071188,"content":"Reacted ❤️ to your message","type":"Generic","is_unsent":false},{"sender_name":"Bilal Hasson","timestamp_ms":1607364045830,"content":"And maybe even a little create time 💚","reactions":[{"reaction":"❤️","actor":"Genevieve Hasson"},{"reaction":"❤️","actor":"Genevieve Hasson"}],"type":"Generic","is_unsent":false},{"sender_name":"Bilal Hasson","timestamp_ms":1607364033022,"content":"I hope you enjoy the rest of your shift my lovely!","reactions":[{"reaction":"❤️","actor":"Genevieve Hasson"},{"reaction":"❤️","actor":"Genevieve Hasson"}],"type":"Generic","is_unsent":false},{"sender_name":"Bilal Hasson","timestamp_ms":1607364020857,"content":"😘","type":"Generic","is_unsent":false},{"sender_name":"Bilal Hasson","timestamp_ms":1607364018910,"content":"💚","type":"Generic","is_unsent":false},{"sender_name":"Bilal Hasson","timestamp_ms":1607364017288,"content":"Yes baby I didn’t answer because I was driving 👌🏼","reactions":[{"reaction":"❤️","actor":"Genevieve Hasson"},{"reaction":"❤️","actor":"Genevieve Hasson"}],"type":"Generic","is_unsent":false},{"sender_name":"Genevieve Hasson","timestamp_ms":1607363901998,"content":"Baby","type":"Generic","is_unsent":false},{"sender_name":"Genevieve Hasson","timestamp_ms":1607363865100,"content":"Bay","type":"Generic","is_unsent":false},{"sender_name":"Genevieve Hasson","timestamp_ms":1607363863643,"content":"Baby","type":"Generic","is_unsent":false},{"sender_name":"Genevieve Hasson","timestamp_ms":1607363858937,"content":"Baby","type":"Generic","is_unsent":false},{"sender_name":"Genevieve Hasson","timestamp_ms":1607363855942,"content":"Baby","type":"Generic","is_unsent":false},{"sender_name":"Genevieve Hasson","timestamp_ms":1607363853965,"content":"Baby","type":"Generic","is_unsent":false},{"sender_name":"Genevieve Hasson","timestamp_ms":1607363848524,"content":"Baby","type":"Generic","is_unsent":false},{"sender_name":"Genevieve Hasson","timestamp_ms":1607363846872,"content":"Baby","type":"Generic","is_unsent":false},{"sender_name":"Genevieve Hasson","timestamp_ms":1607363589949,"content":"Going to see mum?","type":"Generic","is_unsent":false},{"sender_name":"Bilal Hasson","timestamp_ms":1607363164596,"content":"Ah even if it was your time I would stay up for you! 🥰","type":"Generic","is_unsent":false},{"sender_name":"Genevieve Hasson","timestamp_ms":1607362943987,"content":"Oops!","type":"Generic","is_unsent":false},{"sender_name":"Bilal Hasson","timestamp_ms":1607362942366,"content":"Haha yass baby 🥰","type":"Generic","is_unsent":false},{"sender_name":"Genevieve Hasson","timestamp_ms":1607362933574,"content":"Hahah","type":"Generic","is_unsent":false},{"sender_name":"Genevieve Hasson","timestamp_ms":1607362931445,"content":"Your time!","type":"Generic","is_unsent":false},{"sender_name":"Bilal Hasson","timestamp_ms":1607362912190,"content":"9ish your time?","type":"Generic","is_unsent":false},{"sender_name":"Bilal Hasson","timestamp_ms":1607362894996,"content":"Haha","type":"Generic","is_unsent":false},{"sender_name":"Bilal Hasson","timestamp_ms":1607362893677,"content":"Don’t gooooo","type":"Generic","is_unsent":false},{"sender_name":"Genevieve Hasson","timestamp_ms":1607362883547,"content":"I’ll text with you when I can","type":"Generic","is_unsent":false},{"sender_name":"Bilal Hasson","timestamp_ms":1607362881526,"content":"🤣","type":"Generic","is_unsent":false},{"sender_name":"Bilal Hasson","timestamp_ms":1607362880589,"content":"😍","type":"Generic","is_unsent":false},{"sender_name":"Bilal Hasson","timestamp_ms":1607362877547,"content":"I want to be greedy","type":"Generic","is_unsent":false},{"sender_name":"Bilal Hasson","timestamp_ms":1607362873141,"content":"Stay with me!","type":"Generic","is_unsent":false},{"sender_name":"Genevieve Hasson","timestamp_ms":1607362871442,"content":"Can I call you around 9ish?","type":"Generic","is_unsent":false},{"sender_name":"Bilal Hasson","timestamp_ms":1607362870368,"content":"Noooooo","type":"Generic","is_unsent":false},{"sender_name":"Genevieve Hasson","timestamp_ms":1607362847904,"content":"Yes back to work.","type":"Generic","is_unsent":false},{"sender_name":"Bilal Hasson","timestamp_ms":1607362834019,"content":"At least 2-3 already!!","type":"Generic","is_unsent":false},{"sender_name":"Genevieve Hasson","timestamp_ms":1607362826521,"content":"Reacted ❤️ to your message","type":"Generic","is_unsent":false},{"sender_name":"Genevieve Hasson","timestamp_ms":1607362825693,"content":"Reacted ❤️ to your message","type":"Generic","is_unsent":false},{"sender_name":"Genevieve Hasson","timestamp_ms":1607362824949,"content":"Reacted ❤️ to your message","type":"Generic","is_unsent":false},{"sender_name":"Genevieve Hasson","timestamp_ms":1607362823541,"content":"Reacted ❤️ to your message","type":"Generic","is_unsent":false},{"sender_name":"Genevieve Hasson","timestamp_ms":1607362821422,"content":"Reacted ❤️ to your message","type":"Generic","is_unsent":false},{"sender_name":"Genevieve Hasson","timestamp_ms":1607362820290,"content":"Reacted ❤️ to your message","type":"Generic","is_unsent":false},{"sender_name":"Genevieve Hasson","timestamp_ms":1607362817849,"content":"Reacted ❤️ to your message","type":"Generic","is_unsent":false},{"sender_name":"Bilal Hasson","timestamp_ms":1607362814891,"content":"I should be snuggling you, squeezing you","reactions":[{"reaction":"❤️","actor":"Genevieve Hasson"},{"reaction":"❤️","actor":"Genevieve Hasson"}],"type":"Generic","is_unsent":false},{"sender_name":"Genevieve Hasson","timestamp_ms":1607362809361,"content":"We should have ducked a lot by now","reactions":[{"reaction":"❤️","actor":"Bilal Hasson"},{"reaction":"❤️","actor":"Bilal Hasson"}],"type":"Generic","is_unsent":false},{"sender_name":"Bilal Hasson","timestamp_ms":1607362804768,"content":"💚","type":"Generic","is_unsent":false},{"sender_name":"Bilal Hasson","timestamp_ms":1607362803562,"content":"Yes you should!","reactions":[{"reaction":"❤️","actor":"Genevieve Hasson"},{"reaction":"❤️","actor":"Genevieve Hasson"}],"type":"Generic","is_unsent":false},{"sender_name":"Bilal Hasson","timestamp_ms":1607362797898,"content":"Yes!","reactions":[{"reaction":"❤️","actor":"Genevieve Hasson"},{"reaction":"❤️","actor":"Genevieve Hasson"}],"type":"Generic","is_unsent":false},{"sender_name":"Genevieve Hasson","timestamp_ms":1607362777661,"content":"I should be in your arms right now","type":"Generic","is_unsent":false},{"sender_name":"Bilal Hasson","timestamp_ms":1607362773435,"content":"✨","type":"Generic","is_unsent":false},{"sender_name":"Bilal Hasson","timestamp_ms":1607362770960,"content":"With you","reactions":[{"reaction":"❤️","actor":"Genevieve Hasson"},{"reaction":"❤️","actor":"Genevieve Hasson"}],"type":"Generic","is_unsent":false},{"sender_name":"Bilal Hasson","timestamp_ms":1607362768919,"content":"Always","reactions":[{"reaction":"❤️","actor":"Genevieve Hasson"},{"reaction":"❤️","actor":"Genevieve Hasson"}],"type":"Generic","is_unsent":false},{"sender_name":"Bilal Hasson","timestamp_ms":1607362767183,"content":"Just know that I’m here","reactions":[{"reaction":"❤️","actor":"Genevieve Hasson"},{"reaction":"❤️","actor":"Genevieve Hasson"}],"type":"Generic","is_unsent":false},{"sender_name":"Bilal Hasson","timestamp_ms":1607362750301,"content":"I know baby 💚","reactions":[{"reaction":"❤️","actor":"Genevieve Hasson"},{"reaction":"❤️","actor":"Genevieve Hasson"}],"type":"Generic","is_unsent":false},{"sender_name":"Genevieve Hasson","timestamp_ms":1607362737342,"content":"This was not how Christmas was supposed to be","type":"Generic","is_unsent":false},{"sender_name":"Bilal Hasson","timestamp_ms":1607362735009,"content":"Hahaha i don’t know why but that’s funny!","type":"Generic","is_unsent":false},{"sender_name":"Bilal Hasson","timestamp_ms":1607362722923,"share":{"link":"https://media1.giphy.com/media/v1.Y2lkPTA3MTNiODVjMGQ1YmIxMzhhOTY2YWMwNzY3ZmY5NzY1YmE1MDNmNGY0MTliOWY2ZQ/gEvlamTf0dPCf2ExHj/200.gif","original_content_owner":"Comicada"},"type":"Share","is_unsent":false},{"sender_name":"Bilal Hasson","timestamp_ms":1607362719051,"content":"Hehe","type":"Generic","is_unsent":false},{"sender_name":"Bilal Hasson","timestamp_ms":1607362717391,"content":"It’s okay here","type":"Generic","is_unsent":false},{"sender_name":"Genevieve Hasson","timestamp_ms":1607362688108,"content":"Sorry my mind is not focused","type":"Generic","is_unsent":false},{"sender_name":"Bilal Hasson","timestamp_ms":1607362668253,"content":"You are my family 😍","type":"Generic","is_unsent":false},{"sender_name":"Bilal Hasson","timestamp_ms":1607362656379,"content":"💚","type":"Generic","is_unsent":false},{"sender_name":"Bilal Hasson","timestamp_ms":1607362653080,"content":"Yass baby","type":"Generic","is_unsent":false},{"sender_name":"Bilal Hasson","timestamp_ms":1607362648386,"content":"😏","type":"Generic","is_unsent":false},{"sender_name":"Genevieve Hasson","timestamp_ms":1607362643888,"content":"So you’ll stay far away","type":"Generic","is_unsent":false},{"sender_name":"Genevieve Hasson","timestamp_ms":1607362635469,"content":"Correct","type":"Generic","is_unsent":false},{"sender_name":"Genevieve Hasson","timestamp_ms":1607362633163,"content":"You don’t want to be there.....","type":"Generic","is_unsent":false},{"sender_name":"Bilal Hasson","timestamp_ms":1607362616237,"content":"Would you like to rethink that? 🤭","type":"Generic","is_unsent":false},{"sender_name":"Genevieve Hasson","timestamp_ms":1607362594797,"content":"It doesn’t upset me","type":"Generic","is_unsent":false},{"sender_name":"Genevieve Hasson","timestamp_ms":1607362587883,"content":"If you want","type":"Generic","is_unsent":false},{"sender_name":"Genevieve Hasson","timestamp_ms":1607362584287,"content":"You can go there on Christmas","type":"Generic","is_unsent":false},{"sender_name":"Bilal Hasson","timestamp_ms":1607362567759,"content":"We’ll see haha 🤷🏽‍♂️","type":"Generic","is_unsent":false},{"sender_name":"Genevieve Hasson","timestamp_ms":1607362549873,"content":"Don’t you have her Christmas Eve?","type":"Generic","is_unsent":false},{"sender_name":"Bilal Hasson","timestamp_ms":1607362519927,"content":"She’s just asking what’s happening with occasions like Christmas and birthdays","type":"Generic","is_unsent":false},{"sender_name":"Genevieve Hasson","timestamp_ms":1607362424944,"content":"Any alarming emails from EQ?","type":"Generic","is_unsent":false},{"sender_name":"Bilal Hasson","timestamp_ms":1607362421111,"content":"Yasss","type":"Generic","is_unsent":false},{"sender_name":"Genevieve Hasson","timestamp_ms":1607362382078,"content":"Maybe this afternoon!","type":"Generic","is_unsent":false},{"sender_name":"Bilal Hasson","timestamp_ms":1607362381252,"content":"🥰","type":"Generic","is_unsent":false},{"sender_name":"Bilal Hasson","timestamp_ms":1607362379847,"content":"I love it when you get a chance to be creative","type":"Generic","is_unsent":false},{"sender_name":"Bilal Hasson","timestamp_ms":1607362372355,"content":"Awh thats crap baby","type":"Generic","is_unsent":false},{"sender_name":"Genevieve Hasson","timestamp_ms":1607362247982,"content":"No time to be creative","type":"Generic","is_unsent":false},{"sender_name":"Genevieve Hasson","timestamp_ms":1607362233299,"content":"Busy","type":"Generic","is_unsent":false},{"sender_name":"Genevieve Hasson","timestamp_ms":1607362230862,"content":"It’s going ok","type":"Generic","is_unsent":false},{"sender_name":"Bilal Hasson","timestamp_ms":1607362223093,"content":"Other than lunch, what about your day?","type":"Generic","is_unsent":false},{"sender_name":"Bilal Hasson","timestamp_ms":1607362177674,"content":"My day has gone well thanks my love 💚","type":"Generic","is_unsent":false},{"sender_name":"Genevieve Hasson","timestamp_ms":1607362160139,"content":"Yes please Oscar!","reactions":[{"reaction":"❤️","actor":"Bilal Hasson"},{"reaction":"❤️","actor":"Bilal Hasson"}],"type":"Generic","is_unsent":false},{"sender_name":"Genevieve Hasson","timestamp_ms":1607362143520,"content":"It’s fine!","type":"Generic","is_unsent":false},{"sender_name":"Bilal Hasson","timestamp_ms":1607362141740,"content":"Maybe you can snack on me 😏","type":"Generic","is_unsent":false},{"sender_name":"Bilal Hasson","timestamp_ms":1607362135820,"content":"I’m sorry you’re not having a good lunch","type":"Generic","is_unsent":false},{"sender_name":"Bilal Hasson","timestamp_ms":1607362121445,"content":"Awh baby","type":"Generic","is_unsent":false},{"sender_name":"Genevieve Hasson","timestamp_ms":1607361947114,"content":"How is your day?","type":"Generic","is_unsent":false},{"sender_name":"Genevieve Hasson","timestamp_ms":1607361841360,"content":"And cheese!","type":"Generic","is_unsent":false},{"sender_name":"Genevieve Hasson","timestamp_ms":1607361831867,"content":"Nope I’m eating almonds","type":"Generic","is_unsent":false},{"sender_name":"Bilal Hasson","timestamp_ms":1607361819099,"content":"Can you quickly go get something else?","type":"Generic","is_unsent":false},{"sender_name":"Bilal Hasson","timestamp_ms":1607361807951,"content":"Babbyyyy","type":"Generic","is_unsent":false},{"sender_name":"Bilal Hasson","timestamp_ms":1607361804631,"content":"🙈🤣","type":"Generic","is_unsent":false},{"sender_name":"Genevieve Hasson","timestamp_ms":1607361802753,"content":"I gave up","type":"Generic","is_unsent":false},{"sender_name":"Bilal Hasson","timestamp_ms":1607361799060,"content":"If you say so","type":"Generic","is_unsent":false},{"sender_name":"Bilal Hasson","timestamp_ms":1607361795850,"content":"Urmmm","type":"Generic","is_unsent":false},{"sender_name":"Genevieve Hasson","timestamp_ms":1607361781044,"content":"Mac and cheese bowl","type":"Generic","is_unsent":false},{"sender_name":"Bilal Hasson","timestamp_ms":1607361727455,"content":"Looks like potatoes in a creamy sauce?","type":"Generic","is_unsent":false},{"sender_name":"Genevieve Hasson","timestamp_ms":1607361696395,"type":"Generic","is_unsent":false},{"sender_name":"Bilal Hasson","timestamp_ms":1607361664166,"content":"That doesn’t sound good 🤐","type":"Generic","is_unsent":false},{"sender_name":"Genevieve Hasson","timestamp_ms":1607361654483,"content":"Ugh!","type":"Generic","is_unsent":false},{"sender_name":"Genevieve Hasson","timestamp_ms":1607361642505,"content":"A frozen crap","type":"Generic","is_unsent":false},{"sender_name":"Genevieve Hasson","timestamp_ms":1607361631276,"content":"Dunno","type":"Generic","is_unsent":false},{"sender_name":"Bilal Hasson","timestamp_ms":1607361627859,"content":"What is it?","type":"Generic","is_unsent":false},{"sender_name":"Bilal Hasson","timestamp_ms":1607361622893,"content":"Why baby?","type":"Generic","is_unsent":false},{"sender_name":"Bilal Hasson","timestamp_ms":1607361619993,"content":"Noooo","type":"Generic","is_unsent":false},{"sender_name":"Bilal Hasson","timestamp_ms":1607361616882,"content":"🤦🏽‍♂️","type":"Generic","is_unsent":false},{"sender_name":"Bilal Hasson","timestamp_ms":1607361614531,"content":"What?","type":"Generic","is_unsent":false},{"sender_name":"Genevieve Hasson","timestamp_ms":1607361614260,"content":"It’s yuck","type":"Generic","is_unsent":false},{"sender_name":"Genevieve Hasson","timestamp_ms":1607361606229,"content":"Crap","type":"Generic","is_unsent":false},{"sender_name":"Genevieve Hasson","timestamp_ms":1607361603236,"content":"Yes","type":"Generic","is_unsent":false},{"sender_name":"Bilal Hasson","timestamp_ms":1607361596690,"content":"What are you having? 🥰","type":"Generic","is_unsent":false},{"sender_name":"Bilal Hasson","timestamp_ms":1607361584309,"content":"Are you on your lunch now?","type":"Generic","is_unsent":false},{"sender_name":"Genevieve Hasson","timestamp_ms":1607361546577,"content":"Hi","type":"Generic","is_unsent":false},{"sender_name":"Bilal Hasson","timestamp_ms":1607361507259,"content":"Babbyyyyy I fucking love you! 💚","type":"Generic","is_unsent":false},{"sender_name":"Genevieve Hasson","timestamp_ms":1607361488110,"content":"No text when you y have time","type":"Generic","is_unsent":false},{"sender_name":"Genevieve Hasson","timestamp_ms":1607361481703,"content":"Hello!","type":"Generic","is_unsent":false},{"sender_name":"Bilal Hasson","timestamp_ms":1607361478902,"content":"I’m on a call give me 2 secs 😘💚","type":"Generic","is_unsent":false},{"sender_name":"Bilal Hasson","timestamp_ms":1607361469836,"content":"🥰","type":"Generic","is_unsent":false},{"sender_name":"Bilal Hasson","timestamp_ms":1607361468100,"content":"Babyyyyyy","type":"Generic","is_unsent":false},{"sender_name":"Genevieve Hasson","timestamp_ms":1607361297509,"content":"Baby!","type":"Generic","is_unsent":false},{"sender_name":"Genevieve Hasson","timestamp_ms":1607361283081,"content":"Baby!","type":"Generic","is_unsent":false},{"sender_name":"Genevieve Hasson","timestamp_ms":1607361278187,"content":"Baby!","type":"Generic","is_unsent":false},{"sender_name":"Genevieve Hasson","timestamp_ms":1607361274483,"content":"Baby!","type":"Generic","is_unsent":false},{"sender_name":"Genevieve Hasson","timestamp_ms":1607361268881,"content":"Baby!","type":"Generic","is_unsent":false},{"sender_name":"Bilal Hasson","timestamp_ms":1607360202542,"photos":"/genevieve/photos/130327657_384335592638660_833391421951241892_n_222300545947852.jpg","type":"Generic","is_unsent":false},{"sender_name":"Bilal Hasson","timestamp_ms":1607360180016,"content":"I miss you so much!","type":"Generic","is_unsent":false},{"sender_name":"Bilal Hasson","timestamp_ms":1607360174518,"content":"I love you!","type":"Generic","is_unsent":false},{"sender_name":"Bilal Hasson","timestamp_ms":1607360170324,"content":"Babbyyy 🥰","type":"Generic","is_unsent":false},{"sender_name":"Bilal Hasson","timestamp_ms":1607360168710,"audio_files":"/genevieve/audio/audioclip16073601690002182_867319090762914.mp4","type":"Generic","is_unsent":false},{"sender_name":"Genevieve Hasson","timestamp_ms":1607356031742,"content":"Reacted ❤️ to your message","type":"Generic","is_unsent":false},{"sender_name":"Bilal Hasson","timestamp_ms":1607355008225,"content":"Baby, you know that just loving me is all I’d ever need. And forgiving me for my forgetful mind haha","reactions":[{"reaction":"❤️","actor":"Genevieve Hasson"},{"reaction":"❤️","actor":"Genevieve Hasson"}],"type":"Generic","is_unsent":false},{"sender_name":"Genevieve Hasson","timestamp_ms":1607355005539,"content":"And so many other ways I can come up with and not state right now.","reactions":[{"reaction":"❤️","actor":"Bilal Hasson"},{"reaction":"❤️","actor":"Bilal Hasson"}],"type":"Generic","is_unsent":false},{"sender_name":"Bilal Hasson","timestamp_ms":1607354695183,"content":"I love how you’re going to love me!","type":"Generic","is_unsent":false},{"sender_name":"Bilal Hasson","timestamp_ms":1607354680845,"content":"Baby you are wonderful! 🥰","type":"Generic","is_unsent":false},{"sender_name":"Genevieve Hasson","timestamp_ms":1607354588164,"content":"If you allow me to, I’ll spoil you with any and everything you want.","reactions":[{"reaction":"❤️","actor":"Bilal Hasson"},{"reaction":"❤️","actor":"Bilal Hasson"}],"type":"Generic","is_unsent":false},{"sender_name":"Genevieve Hasson","timestamp_ms":1607354512438,"content":"Every moment we are together, I promise to touch you, or be as close as possible to you. I will tell you constantly that I love you.  If you are not home with me, I will be curled up in your shirt smelling you and feeling you near me","reactions":[{"reaction":"❤️","actor":"Bilal Hasson"},{"reaction":"❤️","actor":"Bilal Hasson"}],"type":"Generic","is_unsent":false},{"sender_name":"Genevieve Hasson","timestamp_ms":1607354370643,"content":"Sleep next to you every night with my body touching yours.","reactions":[{"reaction":"❤️","actor":"Bilal Hasson"},{"reaction":"❤️","actor":"Bilal Hasson"}],"type":"Generic","is_unsent":false},{"sender_name":"Genevieve Hasson","timestamp_ms":1607354341246,"content":"Hike, swim, travel, exercise, Rock climb and any other activity we want to do","reactions":[{"reaction":"❤️","actor":"Bilal Hasson"},{"reaction":"❤️","actor":"Bilal Hasson"}],"type":"Generic","is_unsent":false},{"sender_name":"Genevieve Hasson","timestamp_ms":1607354253258,"content":"Read, sing, paint, draw with you","reactions":[{"reaction":"❤️","actor":"Bilal Hasson"},{"reaction":"❤️","actor":"Bilal Hasson"}],"type":"Generic","is_unsent":false},{"sender_name":"Genevieve Hasson","timestamp_ms":1607354221464,"content":"Fix dinner while you relax and code.","reactions":[{"reaction":"❤️","actor":"Bilal Hasson"},{"reaction":"❤️","actor":"Bilal Hasson"}],"type":"Generic","is_unsent":false},{"sender_name":"Genevieve Hasson","timestamp_ms":1607354195133,"content":"Let you be my daddy and fuck me senseless wherever, however, and whenever you want","reactions":[{"reaction":"❤️","actor":"Bilal Hasson"},{"reaction":"❤️","actor":"Bilal Hasson"}],"type":"Generic","is_unsent":false},{"sender_name":"Genevieve Hasson","timestamp_ms":1607354153082,"content":"Draw a bath and relax with you in it.","reactions":[{"reaction":"❤️","actor":"Bilal Hasson"},{"reaction":"❤️","actor":"Bilal Hasson"}],"type":"Generic","is_unsent":false},{"sender_name":"Genevieve Hasson","timestamp_ms":1607354138073,"content":"Suck your delicious cock","reactions":[{"reaction":"❤️","actor":"Bilal Hasson"},{"reaction":"❤️","actor":"Bilal Hasson"}],"type":"Generic","is_unsent":false},{"sender_name":"Genevieve Hasson","timestamp_ms":1607354127034,"content":"Massage your shoulders after a long day.","reactions":[{"reaction":"❤️","actor":"Bilal Hasson"},{"reaction":"❤️","actor":"Bilal Hasson"}],"type":"Generic","is_unsent":false},{"sender_name":"Genevieve Hasson","timestamp_ms":1607354099404,"content":"Run to you when you get home attack you with kisses!","reactions":[{"reaction":"❤️","actor":"Bilal Hasson"},{"reaction":"❤️","actor":"Bilal Hasson"}],"type":"Generic","is_unsent":false},{"sender_name":"Genevieve Hasson","timestamp_ms":1607353824460,"content":"Get your favorite snacks for you","reactions":[{"reaction":"❤️","actor":"Bilal Hasson"},{"reaction":"❤️","actor":"Bilal Hasson"}],"type":"Generic","is_unsent":false},{"sender_name":"Genevieve Hasson","timestamp_ms":1607353800767,"content":"Fill your car with gas for you","reactions":[{"reaction":"❤️","actor":"Bilal Hasson"},{"reaction":"❤️","actor":"Bilal Hasson"}],"type":"Generic","is_unsent":false},{"sender_name":"Genevieve Hasson","timestamp_ms":1607353788103,"content":"Visit you at the office for a lunch date or fuck","reactions":[{"reaction":"❤️","actor":"Bilal Hasson"},{"reaction":"❤️","actor":"Bilal Hasson"}],"type":"Generic","is_unsent":false},{"sender_name":"Genevieve Hasson","timestamp_ms":1607353768326,"content":"Call:text you during the day to remind you.","reactions":[{"reaction":"❤️","actor":"Bilal Hasson"},{"reaction":"❤️","actor":"Bilal Hasson"}],"type":"Generic","is_unsent":false},{"sender_name":"Genevieve Hasson","timestamp_ms":1607353744607,"content":"Leave love notes all around the house","reactions":[{"reaction":"❤️","actor":"Bilal Hasson"},{"reaction":"❤️","actor":"Bilal Hasson"}],"type":"Generic","is_unsent":false},{"sender_name":"Genevieve Hasson","timestamp_ms":1607353708286,"content":"Pack your lunch","reactions":[{"reaction":"❤️","actor":"Bilal Hasson"},{"reaction":"❤️","actor":"Bilal Hasson"}],"type":"Generic","is_unsent":false},{"sender_name":"Genevieve Hasson","timestamp_ms":1607353700206,"content":"I want to \nkiss you every morning\n\nTell you I love you as soon as you wake\n\nPlease Oscar\n\nStart the shower for you so it’s nice and warm when you get in\n\nBring you a cup of coffee while in bed\n\nFix your oats,honey, and peanut butter for you","reactions":[{"reaction":"❤️","actor":"Bilal Hasson"},{"reaction":"❤️","actor":"Bilal Hasson"}],"type":"Generic","is_unsent":false},{"sender_name":"Bilal Hasson","timestamp_ms":1607352729925,"content":"How do you want to love me?","type":"Generic","is_unsent":false},{"sender_name":"Genevieve Hasson","timestamp_ms":1607352647096,"content":"What do you need from me a baby to show you my love?","reactions":[{"reaction":"❤️","actor":"Bilal Hasson"},{"reaction":"❤️","actor":"Bilal Hasson"}],"type":"Generic","is_unsent":false},{"sender_name":"Genevieve Hasson","timestamp_ms":1607352607712,"content":"I’ll think about it.","reactions":[{"reaction":"❤️","actor":"Bilal Hasson"},{"reaction":"❤️","actor":"Bilal Hasson"}],"type":"Generic","is_unsent":false},{"sender_name":"Bilal Hasson","timestamp_ms":1607352580437,"content":"Is there anything else I could do?","type":"Generic","is_unsent":false},{"sender_name":"Genevieve Hasson","timestamp_ms":1607352579234,"content":"Yes.","type":"Generic","is_unsent":false},{"sender_name":"Bilal Hasson","timestamp_ms":1607352570797,"content":"Do you really?","type":"Generic","is_unsent":false},{"sender_name":"Genevieve Hasson","timestamp_ms":1607352224517,"content":"Bilal, I love how you will love me","reactions":[{"reaction":"❤️","actor":"Bilal Hasson"},{"reaction":"❤️","actor":"Bilal Hasson"}],"type":"Generic","is_unsent":false},{"sender_name":"Genevieve Hasson","timestamp_ms":1607352149252,"content":"Reacted ❤️ to your message","type":"Generic","is_unsent":false},{"sender_name":"Bilal Hasson","timestamp_ms":1607352135643,"content":"It feels amazing to be loved so much by you! 🤩😍🥰","type":"Generic","is_unsent":false},{"sender_name":"Bilal Hasson","timestamp_ms":1607352114753,"content":"To wake up to you every morning and say good morning gorgeous, to fuck you awake like you deserve. To bring you breakfast in bed, snuggle with you. Constantly remind you that you’re a beautiful, sexy, goddess. To hang up your clothes, massage your entire body when you’ve had a stressful day, fuck you again after work! Give you millions of kisses and hugs. Go for hikes, tickle you rolling around on the grass, probably fuck you again 😏🤭","reactions":[{"reaction":"❤️","actor":"Genevieve Hasson"},{"reaction":"❤️","actor":"Genevieve Hasson"}],"type":"Generic","is_unsent":false},{"sender_name":"Genevieve Hasson","timestamp_ms":1607351944812,"content":"How does feel to be loved so thoroughly by me?  Do you like it?","type":"Generic","is_unsent":false},{"sender_name":"Genevieve Hasson","timestamp_ms":1607351908405,"content":"How am I supposed to be loved baby?","type":"Generic","is_unsent":false},{"sender_name":"Bilal Hasson","timestamp_ms":1607351894986,"content":"🌞🌗✨🥰😘💚","type":"Generic","is_unsent":false},{"sender_name":"Genevieve Hasson","timestamp_ms":1607351894732,"content":"Reacted ❤️ to your message","type":"Generic","is_unsent":false},{"sender_name":"Genevieve Hasson","timestamp_ms":1607351890885,"content":"Reacted ❤️ to your message","type":"Generic","is_unsent":false},{"sender_name":"Bilal Hasson","timestamp_ms":1607351885977,"content":"I love you so so so much baby!","reactions":[{"reaction":"❤️","actor":"Genevieve Hasson"},{"reaction":"❤️","actor":"Genevieve Hasson"}],"type":"Generic","is_unsent":false},{"sender_name":"Genevieve Hasson","timestamp_ms":1607351882993,"content":"I never thought it possible to love a person so much!","reactions":[{"reaction":"❤️","actor":"Bilal Hasson"},{"reaction":"❤️","actor":"Bilal Hasson"}],"type":"Generic","is_unsent":false},{"sender_name":"Bilal Hasson","timestamp_ms":1607351871734,"content":"No need to thank me baby 🥰 this is just how it’s going to be from now on my love 😘💚 I will show you how you were meant to be loved 💚🥰","reactions":[{"reaction":"❤️","actor":"Genevieve Hasson"},{"reaction":"❤️","actor":"Genevieve Hasson"}],"type":"Generic","is_unsent":false},{"sender_name":"Genevieve Hasson","timestamp_ms":1607351801274,"content":"So so so much","reactions":[{"reaction":"❤️","actor":"Bilal Hasson"},{"reaction":"❤️","actor":"Bilal Hasson"}],"type":"Generic","is_unsent":false},{"sender_name":"Genevieve Hasson","timestamp_ms":1607351794745,"content":"I love you 💙💙💙","reactions":[{"reaction":"❤️","actor":"Bilal Hasson"},{"reaction":"❤️","actor":"Bilal Hasson"}],"type":"Generic","is_unsent":false},{"sender_name":"Genevieve Hasson","timestamp_ms":1607351786425,"content":"Thank you","reactions":[{"reaction":"❤️","actor":"Bilal Hasson"},{"reaction":"❤️","actor":"Bilal Hasson"}],"type":"Generic","is_unsent":false},{"sender_name":"Genevieve Hasson","timestamp_ms":1607351781161,"content":"Bilal 💙","reactions":[{"reaction":"❤️","actor":"Bilal Hasson"},{"reaction":"❤️","actor":"Bilal Hasson"}],"type":"Generic","is_unsent":false},{"sender_name":"Genevieve Hasson","timestamp_ms":1607351767568,"content":"Reacted ❤️ to your message","type":"Generic","is_unsent":false},{"sender_name":"Bilal Hasson","timestamp_ms":1607351583461,"content":"Not unnecessary to do whatever I can to make my wife happy. 😘 I will do anything and everything in my power! That is my sole duty to ensure your safety and happiness 💚😘🥰","reactions":[{"reaction":"❤️","actor":"Genevieve Hasson"},{"reaction":"❤️","actor":"Genevieve Hasson"}],"type":"Generic","is_unsent":false},{"sender_name":"Genevieve Hasson","timestamp_ms":1607351461759,"content":"So unnecessary","type":"Generic","is_unsent":false},{"sender_name":"Genevieve Hasson","timestamp_ms":1607351422628,"content":"Reacted ❤️ to your message","type":"Generic","is_unsent":false},{"sender_name":"Genevieve Hasson","timestamp_ms":1607351421442,"content":"You should never spend money on me","type":"Generic","is_unsent":false},{"sender_name":"Bilal Hasson","timestamp_ms":1607350877348,"content":"Yes baby 😘 you deserve them! You work so hard 💚","reactions":[{"reaction":"❤️","actor":"Genevieve Hasson"},{"reaction":"❤️","actor":"Genevieve Hasson"}],"type":"Generic","is_unsent":false},{"sender_name":"Genevieve Hasson","timestamp_ms":1607350322455,"photos":"/genevieve/photos/129667571_1635510346634250_5799766129385131006_n_866409857438517.jpg","reactions":[{"reaction":"❤️","actor":"Bilal Hasson"},{"reaction":"❤️","actor":"Bilal Hasson"}],"type":"Generic","is_unsent":false},{"sender_name":"Genevieve Hasson","timestamp_ms":1607350284753,"content":"You got me flowers","reactions":[{"reaction":"❤️","actor":"Bilal Hasson"},{"reaction":"❤️","actor":"Bilal Hasson"}],"type":"Generic","is_unsent":false},{"sender_name":"Genevieve Hasson","timestamp_ms":1607350276416,"content":"Baby","reactions":[{"reaction":"❤️","actor":"Bilal Hasson"},{"reaction":"❤️","actor":"Bilal Hasson"}],"type":"Generic","is_unsent":false},{"sender_name":"Genevieve Hasson","timestamp_ms":1607350271237,"content":"Reacted ❤️ to your message","type":"Generic","is_unsent":false},{"sender_name":"Genevieve Hasson","timestamp_ms":1607350269324,"content":"Reacted ❤️ to your message","type":"Generic","is_unsent":false},{"sender_name":"Genevieve Hasson","timestamp_ms":1607350268324,"content":"Reacted ❤️ to your message","type":"Generic","is_unsent":false},{"sender_name":"Genevieve Hasson","timestamp_ms":1607350267045,"content":"Reacted ❤️ to your message","type":"Generic","is_unsent":false},{"sender_name":"Genevieve Hasson","timestamp_ms":1607350266334,"content":"Reacted ❤️ to your message","type":"Generic","is_unsent":false},{"sender_name":"Genevieve Hasson","timestamp_ms":1607350265492,"content":"Reacted ❤️ to your message","type":"Generic","is_unsent":false},{"sender_name":"Bilal Hasson","timestamp_ms":1607347082869,"photos":"/genevieve/photos/128934155_1052193665204695_8128914724533917424_n_138417651137246.jpg","reactions":[{"reaction":"❤️","actor":"Genevieve Hasson"},{"reaction":"❤️","actor":"Genevieve Hasson"}],"type":"Generic","is_unsent":false},{"sender_name":"Bilal Hasson","timestamp_ms":1607346583119,"content":"💚🥰","reactions":[{"reaction":"❤️","actor":"Genevieve Hasson"},{"reaction":"❤️","actor":"Genevieve Hasson"}],"type":"Generic","is_unsent":false},{"sender_name":"Bilal Hasson","timestamp_ms":1607346581281,"content":"Message when you can 😘","reactions":[{"reaction":"❤️","actor":"Genevieve Hasson"},{"reaction":"❤️","actor":"Genevieve Hasson"}],"type":"Generic","is_unsent":false},{"sender_name":"Bilal Hasson","timestamp_ms":1607346575350,"content":"Have an amazing bay my love!","reactions":[{"reaction":"❤️","actor":"Genevieve Hasson"},{"reaction":"❤️","actor":"Genevieve Hasson"}],"type":"Generic","is_unsent":false},{"sender_name":"Bilal Hasson","timestamp_ms":1607346561121,"content":"You’re so bloody delicious! 😍","reactions":[{"reaction":"❤️","actor":"Genevieve Hasson"},{"reaction":"❤️","actor":"Genevieve Hasson"}],"type":"Generic","is_unsent":false},{"sender_name":"Bilal Hasson","timestamp_ms":1607346540532,"content":"I fucking love you! 😘","reactions":[{"reaction":"❤️","actor":"Genevieve Hasson"},{"reaction":"❤️","actor":"Genevieve Hasson"}],"type":"Generic","is_unsent":false},{"sender_name":"Genevieve Hasson","timestamp_ms":1607344475366,"content":"Reacted ❤️ to your message","type":"Generic","is_unsent":false},{"sender_name":"Bilal Hasson","timestamp_ms":1607344277933,"content":"Babbyy! Get in your car, warm it up, and pull your fucking pants down! 👅","reactions":[{"reaction":"❤️","actor":"Genevieve Hasson"},{"reaction":"❤️","actor":"Genevieve Hasson"}],"type":"Generic","is_unsent":false},{"sender_name":"Genevieve Hasson","timestamp_ms":1607344221649,"content":"I’d say come swim in my loch but it’s too cold to pull my pants down!","reactions":[{"reaction":"❤️","actor":"Bilal Hasson"},{"reaction":"❤️","actor":"Bilal Hasson"}],"type":"Generic","is_unsent":false},{"sender_name":"Genevieve Hasson","timestamp_ms":1607344186359,"content":"Baby! I’m so horny!","reactions":[{"reaction":"❤️","actor":"Bilal Hasson"},{"reaction":"❤️","actor":"Bilal Hasson"}],"type":"Generic","is_unsent":false},{"sender_name":"Bilal Hasson","timestamp_ms":1607344090102,"content":"😏","type":"Generic","is_unsent":false},{"sender_name":"Bilal Hasson","timestamp_ms":1607344087999,"content":"Mmmm baby!!","type":"Generic","is_unsent":false},{"sender_name":"Genevieve Hasson","timestamp_ms":1607344068748,"content":"You deserve a hard nipple bite and a tug on your balls!","reactions":[{"reaction":"❤️","actor":"Bilal Hasson"},{"reaction":"❤️","actor":"Bilal Hasson"}],"type":"Generic","is_unsent":false},{"sender_name":"Bilal Hasson","timestamp_ms":1607344043078,"content":"I deserved that baby!","type":"Generic","is_unsent":false},{"sender_name":"Bilal Hasson","timestamp_ms":1607344033561,"content":"Awch!","type":"Generic","is_unsent":false},{"sender_name":"Genevieve Hasson","timestamp_ms":1607343977234,"content":"There’s your spanking!","reactions":[{"reaction":"❤️","actor":"Bilal Hasson"},{"reaction":"❤️","actor":"Bilal Hasson"}],"type":"Generic","is_unsent":false},{"sender_name":"Genevieve Hasson","timestamp_ms":1607343956211,"reactions":[{"reaction":"❤️","actor":"Bilal Hasson"},{"reaction":"❤️","actor":"Bilal Hasson"}],"share":{"link":"https://media0.giphy.com/media/v1.Y2lkPTA3MTNiODVjN2E2NTZhMjFiNmVjOGVhYjA5MTg4OTljZThkNjRhMjY2NDA1NmM2OQ/s56HRsKc3rAxq/200.gif"},"type":"Share","is_unsent":false},{"sender_name":"Genevieve Hasson","timestamp_ms":1607343945941,"content":"Baby!  Don’t ever leave me again!","reactions":[{"reaction":"❤️","actor":"Bilal Hasson"},{"reaction":"❤️","actor":"Bilal Hasson"}],"type":"Generic","is_unsent":false},{"sender_name":"Genevieve Hasson","timestamp_ms":1607342542090,"audio_files":"/genevieve/audio/audioclip16073425420006199_426028501761352.mp4","reactions":[{"reaction":"❤️","actor":"Bilal Hasson"},{"reaction":"❤️","actor":"Bilal Hasson"}],"type":"Generic","is_unsent":false},{"sender_name":"Genevieve Hasson","timestamp_ms":1607341261325,"content":"I miss you!","reactions":[{"reaction":"❤️","actor":"Bilal Hasson"},{"reaction":"❤️","actor":"Bilal Hasson"}],"type":"Generic","is_unsent":false},{"sender_name":"Genevieve Hasson","timestamp_ms":1607341254616,"content":"Baby","reactions":[{"reaction":"❤️","actor":"Bilal Hasson"},{"reaction":"❤️","actor":"Bilal Hasson"}],"type":"Generic","is_unsent":false},{"sender_name":"Genevieve Hasson","timestamp_ms":1607341251143,"content":"Baby!","reactions":[{"reaction":"❤️","actor":"Bilal Hasson"},{"reaction":"❤️","actor":"Bilal Hasson"}],"type":"Generic","is_unsent":false},{"sender_name":"Genevieve Hasson","timestamp_ms":1607339608128,"content":"You don’t need to make me your, I already am.","reactions":[{"reaction":"❤️","actor":"Bilal Hasson"},{"reaction":"❤️","actor":"Bilal Hasson"}],"type":"Generic","is_unsent":false},{"sender_name":"Genevieve Hasson","timestamp_ms":1607339406263,"content":"Yes please love on me!","reactions":[{"reaction":"❤️","actor":"Bilal Hasson"},{"reaction":"❤️","actor":"Bilal Hasson"}],"type":"Generic","is_unsent":false},{"sender_name":"Genevieve Hasson","timestamp_ms":1607339386719,"content":"Reacted ❤️ to your message","type":"Generic","is_unsent":false},{"sender_name":"Genevieve Hasson","timestamp_ms":1607339371662,"content":"Reacted ❤️ to your message","type":"Generic","is_unsent":false},{"sender_name":"Genevieve Hasson","timestamp_ms":1607339315204,"content":"Baby!","reactions":[{"reaction":"❤️","actor":"Bilal Hasson"},{"reaction":"❤️","actor":"Bilal Hasson"}],"type":"Generic","is_unsent":false},{"sender_name":"Genevieve Hasson","timestamp_ms":1607339311205,"content":"Baby!","reactions":[{"reaction":"❤️","actor":"Bilal Hasson"},{"reaction":"❤️","actor":"Bilal Hasson"}],"type":"Generic","is_unsent":false},{"sender_name":"Genevieve Hasson","timestamp_ms":1607339302451,"content":"Reacted ❤️ to your message","type":"Generic","is_unsent":false},{"sender_name":"Genevieve Hasson","timestamp_ms":1607339301717,"content":"Reacted ❤️ to your message","type":"Generic","is_unsent":false},{"sender_name":"Genevieve Hasson","timestamp_ms":1607339295149,"content":"Reacted ❤️ to your message","type":"Generic","is_unsent":false},{"sender_name":"Genevieve Hasson","timestamp_ms":1607339293353,"content":"Reacted ❤️ to your message","type":"Generic","is_unsent":false},{"sender_name":"Genevieve Hasson","timestamp_ms":1607339292587,"content":"Reacted ❤️ to your message","type":"Generic","is_unsent":false},{"sender_name":"Genevieve Hasson","timestamp_ms":1607339291754,"content":"Reacted ❤️ to your message","type":"Generic","is_unsent":false},{"sender_name":"Genevieve Hasson","timestamp_ms":1607339290963,"content":"Reacted ❤️ to your message","type":"Generic","is_unsent":false},{"sender_name":"Genevieve Hasson","timestamp_ms":1607339290156,"content":"Reacted ❤️ to your message","type":"Generic","is_unsent":false},{"sender_name":"Bilal Hasson","timestamp_ms":1607337327133,"audio_files":"/genevieve/audio/audioclip160733732700010240_750032398928747.mp4","reactions":[{"reaction":"❤️","actor":"Genevieve Hasson"},{"reaction":"❤️","actor":"Genevieve Hasson"}],"type":"Generic","is_unsent":false},{"sender_name":"Bilal Hasson","timestamp_ms":1607332852358,"audio_files":"/genevieve/audio/audioclip160733285200036896_401180514459917.mp4","reactions":[{"reaction":"❤️","actor":"Genevieve Hasson"},{"reaction":"❤️","actor":"Genevieve Hasson"}],"type":"Generic","is_unsent":false},{"sender_name":"Bilal Hasson","timestamp_ms":1607332841339,"content":"Good morning gorgeous!","reactions":[{"reaction":"❤️","actor":"Genevieve Hasson"},{"reaction":"❤️","actor":"Genevieve Hasson"}],"type":"Generic","is_unsent":false},{"sender_name":"Bilal Hasson","timestamp_ms":1607332833248,"content":"I fucking love you! 😍","reactions":[{"reaction":"❤️","actor":"Genevieve Hasson"},{"reaction":"❤️","actor":"Genevieve Hasson"}],"type":"Generic","is_unsent":false},{"sender_name":"Bilal Hasson","timestamp_ms":1607332824751,"content":"😘","reactions":[{"reaction":"❤️","actor":"Genevieve Hasson"},{"reaction":"❤️","actor":"Genevieve Hasson"}],"type":"Generic","is_unsent":false},{"sender_name":"Bilal Hasson","timestamp_ms":1607332823778,"content":"🥰","reactions":[{"reaction":"❤️","actor":"Genevieve Hasson"},{"reaction":"❤️","actor":"Genevieve Hasson"}],"type":"Generic","is_unsent":false},{"sender_name":"Bilal Hasson","timestamp_ms":1607332821522,"content":"💚💚💚","reactions":[{"reaction":"❤️","actor":"Genevieve Hasson"},{"reaction":"❤️","actor":"Genevieve Hasson"}],"type":"Generic","is_unsent":false},{"sender_name":"Bilal Hasson","timestamp_ms":1607332819117,"content":"Babbbyyyy","reactions":[{"reaction":"❤️","actor":"Genevieve Hasson"},{"reaction":"❤️","actor":"Genevieve Hasson"}],"type":"Generic","is_unsent":false},{"sender_name":"Bilal Hasson","timestamp_ms":1607332817225,"content":"Baby","reactions":[{"reaction":"❤️","actor":"Genevieve Hasson"},{"reaction":"❤️","actor":"Genevieve Hasson"}],"type":"Generic","is_unsent":false},{"sender_name":"Bilal Hasson","timestamp_ms":1607332815974,"content":"Babbyy","reactions":[{"reaction":"❤️","actor":"Genevieve Hasson"},{"reaction":"❤️","actor":"Genevieve Hasson"}],"type":"Generic","is_unsent":false},{"sender_name":"Genevieve Hasson","timestamp_ms":1607319776728,"photos":"/genevieve/photos/130400028_3393995314062656_1020558771377441453_n_2980722122156042.jpg","reactions":[{"reaction":"❤️","actor":"Bilal Hasson"},{"reaction":"❤️","actor":"Bilal Hasson"}],"type":"Generic","is_unsent":false},{"sender_name":"Genevieve Hasson","timestamp_ms":1607319768805,"content":"Bilal,\nYou occupy every space in my\n💋mind\n💋heart\n💋body\n💋soul\n💋past\n💋present\n💋future\n💋entire being\n\nThere are many times in my life that I have felt consumed by fear, worry, anxiety, self doubt, depression, anger, humiliation, despair, pain, guilt and many other negative emotions.  It’s easy to be consumed by the negative emotions because they are so overwhelming.\n\nBut I have NEVER been consumed with LOVE!  My love for you is wrapped in every fiber of my being.  Your love for me is wrapped tightly around me as a protective layer.  \n\nI never thought it was possible to feel these 3 emotions together\n💙Love\n💙Happiness\n💙Hope\nBut you have been able to wrap these 3 into my heart, body, & soul.\n\nBilal, you have given me the two of the most precious gifts: your love to me and letting me love you.\n\nBaby, I cannot express with words what I feel for you.  These words don’t do my Love justice.\n\nI’ve also attached a poem that just came to me after you fell asleep.  \nI love you Baby💙💚💙💚","reactions":[{"reaction":"❤️","actor":"Bilal Hasson"},{"reaction":"❤️","actor":"Bilal Hasson"}],"type":"Generic","is_unsent":false},{"sender_name":"Genevieve Hasson","timestamp_ms":1607302670886,"photos":"/genevieve/photos/129727487_194719779028404_3866515747425765875_n_843580753074814.jpg","reactions":[{"reaction":"❤️","actor":"Bilal Hasson"},{"reaction":"❤️","actor":"Bilal Hasson"}],"type":"Generic","is_unsent":false},{"sender_name":"Genevieve Hasson","timestamp_ms":1607302650678,"content":"Reacted ❤️ to your message","type":"Generic","is_unsent":false},{"sender_name":"Bilal Hasson","timestamp_ms":1607302608772,"audio_files":"/genevieve/audio/audioclip160730260900027306_435481404132233.mp4","reactions":[{"reaction":"❤️","actor":"Genevieve Hasson"},{"reaction":"❤️","actor":"Genevieve Hasson"}],"type":"Generic","is_unsent":false},{"sender_name":"Genevieve Hasson","timestamp_ms":1607302603209,"content":"If you can’t sleep I’ll be here!","type":"Generic","is_unsent":false},{"sender_name":"Genevieve Hasson","timestamp_ms":1607302595144,"content":"It’s your bed time baby!","type":"Generic","is_unsent":false},{"sender_name":"Genevieve Hasson","timestamp_ms":1607302355196,"audio_files":"/genevieve/audio/audioclip160730235500028026_2003739199769204.mp4","type":"Generic","is_unsent":false},{"sender_name":"Genevieve Hasson","timestamp_ms":1607302327927,"audio_files":"/genevieve/audio/audioclip16073023280008010_390091895600230.mp4","reactions":[{"reaction":"❤️","actor":"Bilal Hasson"},{"reaction":"❤️","actor":"Bilal Hasson"}],"type":"Generic","is_unsent":false},{"sender_name":"Bilal Hasson","timestamp_ms":1607302278449,"audio_files":"/genevieve/audio/audioclip160730227800018552_1189445911490436.mp4","type":"Generic","is_unsent":false},{"sender_name":"Genevieve Hasson","timestamp_ms":1607302269461,"reactions":[{"reaction":"❤️","actor":"Bilal Hasson"},{"reaction":"❤️","actor":"Bilal Hasson"}],"share":{"link":"https://www.instagram.com/p/CIehusaF-Mk/","share_text":"Evening sketch: I was a ballet dancer for 15 years.  I loved it and wanted to be a ballerina 🩰 #myart #mysketch #mydrawing","original_content_owner":"_gigihasson_"},"type":"Share","is_unsent":false},{"sender_name":"Genevieve Hasson","timestamp_ms":1607302193085,"audio_files":"/genevieve/audio/audioclip160730219300041261_872503506890657.mp4","type":"Generic","is_unsent":false},{"sender_name":"Genevieve Hasson","timestamp_ms":1607302120323,"content":"Reacted ❤️ to your message","type":"Generic","is_unsent":false},{"sender_name":"Genevieve Hasson","timestamp_ms":1607302119497,"content":"Reacted ❤️ to your message","type":"Generic","is_unsent":false},{"sender_name":"Genevieve Hasson","timestamp_ms":1607302118742,"content":"Reacted ❤️ to your message","type":"Generic","is_unsent":false},{"sender_name":"Bilal Hasson","timestamp_ms":1607302106385,"audio_files":"/genevieve/audio/audioclip160730210600018459_2918804538389628.mp4","type":"Generic","is_unsent":false},{"sender_name":"Bilal Hasson","timestamp_ms":1607301950721,"content":"🥰","reactions":[{"reaction":"❤️","actor":"Genevieve Hasson"},{"reaction":"❤️","actor":"Genevieve Hasson"}],"type":"Generic","is_unsent":false},{"sender_name":"Bilal Hasson","timestamp_ms":1607301947826,"content":"Well done baby","reactions":[{"reaction":"❤️","actor":"Genevieve Hasson"},{"reaction":"❤️","actor":"Genevieve Hasson"}],"type":"Generic","is_unsent":false},{"sender_name":"Bilal Hasson","timestamp_ms":1607301943355,"content":"I love it!","reactions":[{"reaction":"❤️","actor":"Genevieve Hasson"},{"reaction":"❤️","actor":"Genevieve Hasson"}],"type":"Generic","is_unsent":false},{"sender_name":"Genevieve Hasson","timestamp_ms":1607301940447,"content":"You need to get to sleep.","type":"Generic","is_unsent":false},{"sender_name":"Genevieve Hasson","timestamp_ms":1607301934618,"content":"See I’m taking my compliments!","type":"Generic","is_unsent":false},{"sender_name":"Bilal Hasson","timestamp_ms":1607301928456,"content":"Yes you can!","type":"Generic","is_unsent":false},{"sender_name":"Genevieve Hasson","timestamp_ms":1607301913291,"content":"Yes, I can draw!","reactions":[{"reaction":"❤️","actor":"Bilal Hasson"},{"reaction":"❤️","actor":"Bilal Hasson"}],"type":"Generic","is_unsent":false},{"sender_name":"Genevieve Hasson","timestamp_ms":1607301905167,"photos":"/genevieve/photos/129780519_985219501884262_6134615352840763985_n_568293297370939.jpg","reactions":[{"reaction":"❤️","actor":"Bilal Hasson"},{"reaction":"❤️","actor":"Bilal Hasson"}],"type":"Generic","is_unsent":false},{"sender_name":"Bilal Hasson","timestamp_ms":1607301886824,"content":"💚","type":"Generic","is_unsent":false},{"sender_name":"Bilal Hasson","timestamp_ms":1607301885628,"content":"You’re so fucking talented! 😘","type":"Generic","is_unsent":false},{"sender_name":"Bilal Hasson","timestamp_ms":1607301860408,"content":"Baby thats bloody amazing! 😍","type":"Generic","is_unsent":false},{"sender_name":"Genevieve Hasson","timestamp_ms":1607301838780,"photos":"/genevieve/photos/129720840_496537894658624_3048278698700663909_n_1199312310471291.jpg","reactions":[{"reaction":"❤️","actor":"Bilal Hasson"},{"reaction":"❤️","actor":"Bilal Hasson"}],"type":"Generic","is_unsent":false},{"sender_name":"Bilal Hasson","timestamp_ms":1607301836643,"content":"🥰","type":"Generic","is_unsent":false},{"sender_name":"Bilal Hasson","timestamp_ms":1607301834663,"content":"Oo I’d love to see!","type":"Generic","is_unsent":false},{"sender_name":"Bilal Hasson","timestamp_ms":1607301829643,"content":"Yass!","type":"Generic","is_unsent":false},{"sender_name":"Genevieve Hasson","timestamp_ms":1607301810253,"content":"Figured you could see first","type":"Generic","is_unsent":false},{"sender_name":"Genevieve Hasson","timestamp_ms":1607301799641,"content":"Just finished a sketch as we have been chatting","type":"Generic","is_unsent":false},{"sender_name":"Genevieve Hasson","timestamp_ms":1607301776296,"content":"I like all of the above!","type":"Generic","is_unsent":false},{"sender_name":"Genevieve Hasson","timestamp_ms":1607301763454,"content":"Reacted ❤️ to your message","type":"Generic","is_unsent":false},{"sender_name":"Bilal Hasson","timestamp_ms":1607301691177,"content":"I just had a warm feeling when I heard you sing. Like we were together, happy, enjoying ourselves, having Christmas dinner, surrounded by family 🥰 and then we leaving to go home and fuck like crazy!","reactions":[{"reaction":"❤️","actor":"Genevieve Hasson"},{"reaction":"❤️","actor":"Genevieve Hasson"}],"type":"Generic","is_unsent":false},{"sender_name":"Genevieve Hasson","timestamp_ms":1607301634566,"photos":"/genevieve/photos/129736206_922999404899937_1544646973913112024_n_840962879987144.jpg","type":"Generic","is_unsent":false},{"sender_name":"Genevieve Hasson","timestamp_ms":1607301621470,"content":"Let’s not push it....","type":"Generic","is_unsent":false},{"sender_name":"Bilal Hasson","timestamp_ms":1607301606781,"content":"🤣🤣 really! I think at least 4","type":"Generic","is_unsent":false},{"sender_name":"Genevieve Hasson","timestamp_ms":1607301413344,"content":"What did I do that is amazing!","type":"Generic","is_unsent":false},{"sender_name":"Genevieve Hasson","timestamp_ms":1607301350177,"content":"My hypothesis is 3 songs","reactions":[{"reaction":"❤️","actor":"Bilal Hasson"},{"reaction":"❤️","actor":"Bilal Hasson"}],"type":"Generic","is_unsent":false},{"sender_name":"Bilal Hasson","timestamp_ms":1607301332636,"content":"Hearing you sing that really made me want to be with you thins christmas!","type":"Generic","is_unsent":false},{"sender_name":"Genevieve Hasson","timestamp_ms":1607301322939,"content":"I’m conducting a science experiment to see how long I can tolerate Xmas music.","reactions":[{"reaction":"❤️","actor":"Bilal Hasson"},{"reaction":"❤️","actor":"Bilal Hasson"}],"type":"Generic","is_unsent":false},{"sender_name":"Bilal Hasson","timestamp_ms":1607301318698,"content":"You’re so fucking amazing!","type":"Generic","is_unsent":false},{"sender_name":"Bilal Hasson","timestamp_ms":1607301311679,"content":"Awwwwww baby 🥰","type":"Generic","is_unsent":false},{"sender_name":"Genevieve Hasson","timestamp_ms":1607301292736,"audio_files":"/genevieve/audio/audioclip160730129200012213_423725588658831.mp4","type":"Generic","is_unsent":false},{"sender_name":"Genevieve Hasson","timestamp_ms":1607301257533,"content":"It’s late.  I hate you going, but your sleeping is so important to me","type":"Generic","is_unsent":false},{"sender_name":"Genevieve Hasson","timestamp_ms":1607301227397,"content":"Are you tired baby!","type":"Generic","is_unsent":false},{"sender_name":"Genevieve Hasson","timestamp_ms":1607301212957,"content":"💙💚💙💚","reactions":[{"reaction":"❤️","actor":"Bilal Hasson"},{"reaction":"❤️","actor":"Bilal Hasson"}],"type":"Generic","is_unsent":false},{"sender_name":"Bilal Hasson","timestamp_ms":1607301211609,"content":"😘","type":"Generic","is_unsent":false},{"sender_name":"Bilal Hasson","timestamp_ms":1607301207179,"content":"I did, because I know how much you appreciate the written word.","type":"Generic","is_unsent":false},{"sender_name":"Genevieve Hasson","timestamp_ms":1607301166498,"content":"It will never be a thought in my mind again.  Your words make everything clear to me.  I can tell you took care with everyone you wrote.","reactions":[{"reaction":"❤️","actor":"Bilal Hasson"},{"reaction":"❤️","actor":"Bilal Hasson"}],"type":"Generic","is_unsent":false},{"sender_name":"Genevieve Hasson","timestamp_ms":1607301116463,"content":"I have no doubts or guilt on any of this after reading that.","reactions":[{"reaction":"❤️","actor":"Bilal Hasson"},{"reaction":"❤️","actor":"Bilal Hasson"}],"type":"Generic","is_unsent":false},{"sender_name":"Genevieve Hasson","timestamp_ms":1607301081671,"content":"Reacted ❤️ to your message","type":"Generic","is_unsent":false},{"sender_name":"Bilal Hasson","timestamp_ms":1607301042780,"content":"I feel like an idiot because everyone, all of my friends/family told me to stay away, but I thought I could make it work. \n\nI feel like I should never have even started anything with her. \n\nI feel sad that I cannot give Ramiza a mother and father that like each other. \n\nI feel glad that Ramiza has a mother that takes care of her, and that I never have to worry about her safety. \n\nI feel happy that I’ve met you, and that you’re kind enough to see past all of my problems and still love me. That you’d see Ramiza as being part of our family. It means so much to me. You are my family.","reactions":[{"reaction":"❤️","actor":"Genevieve Hasson"},{"reaction":"❤️","actor":"Genevieve Hasson"}],"type":"Generic","is_unsent":false},{"sender_name":"Genevieve Hasson","timestamp_ms":1607300888700,"content":"You’ve made me stronger","reactions":[{"reaction":"❤️","actor":"Bilal Hasson"},{"reaction":"❤️","actor":"Bilal Hasson"}],"type":"Generic","is_unsent":false},{"sender_name":"Genevieve Hasson","timestamp_ms":1607300755341,"content":"I’m glad Ramiza is feeling better that is all that really matters ❤️","reactions":[{"reaction":"❤️","actor":"Bilal Hasson"},{"reaction":"❤️","actor":"Bilal Hasson"}],"type":"Generic","is_unsent":false},{"sender_name":"Genevieve Hasson","timestamp_ms":1607300714090,"content":"The relationship between you and EQ about R","type":"Generic","is_unsent":false},{"sender_name":"Genevieve Hasson","timestamp_ms":1607300685136,"audio_files":"/genevieve/audio/audioclip160730068500031718_424633818552964.mp4","type":"Generic","is_unsent":false},{"sender_name":"Genevieve Hasson","timestamp_ms":1607300592381,"content":"True or false?","type":"Generic","is_unsent":false},{"sender_name":"Genevieve Hasson","timestamp_ms":1607300561950,"content":"I worry you feel so much pain about all of this and just keep it inside because you don’t want to share it with me (for fear of making me feel bad).","type":"Generic","is_unsent":false},{"sender_name":"Bilal Hasson","timestamp_ms":1607300411532,"content":"This course of events were bound to happen at some point, our getting together may have been a catalyst, however, don’t once think that it’s your fault. \n\nYou can’t always blame yourself for everything baby. Nothing that I do, or the consequences of my actions, are to be blamed by you. I certainly don’t blame you. And I don’t think you should blame yourself either. \n\nIt was going to happen sooner or later.","type":"Generic","is_unsent":false},{"sender_name":"Genevieve Hasson","timestamp_ms":1607299775146,"audio_files":"/genevieve/audio/audioclip160729977500024752_715599065738299.mp4","type":"Generic","is_unsent":false},{"sender_name":"Bilal Hasson","timestamp_ms":1607299673376,"content":"Why do you feel like it’s your fault?","type":"Generic","is_unsent":false},{"sender_name":"Genevieve Hasson","timestamp_ms":1607299646778,"content":"Reacted ❤️ to your message","type":"Generic","is_unsent":false},{"sender_name":"Bilal Hasson","timestamp_ms":1607299642239,"content":"She’s better thanks 🥰","reactions":[{"reaction":"❤️","actor":"Genevieve Hasson"},{"reaction":"❤️","actor":"Genevieve Hasson"}],"type":"Generic","is_unsent":false},{"sender_name":"Genevieve Hasson","timestamp_ms":1607299620670,"content":"And now you don’t have her and I feel like it’s my fault.","type":"Generic","is_unsent":false},{"sender_name":"Genevieve Hasson","timestamp_ms":1607299582480,"content":"I thought if you and her today and how you had Sunday’s with her","type":"Generic","is_unsent":false},{"sender_name":"Genevieve Hasson","timestamp_ms":1607299558917,"content":"How is Ramiza?","type":"Generic","is_unsent":false},{"sender_name":"Bilal Hasson","timestamp_ms":1607299500528,"content":"I think I’ve already forgotten my past 🤭 my brain is good for some things","type":"Generic","is_unsent":false},{"sender_name":"Bilal Hasson","timestamp_ms":1607299455749,"content":"I know you are my lovely 😘","type":"Generic","is_unsent":false},{"sender_name":"Bilal Hasson","timestamp_ms":1607299444134,"content":"But still","type":"Generic","is_unsent":false},{"sender_name":"Genevieve Hasson","timestamp_ms":1607299441929,"content":"Someday, if you want to I’m here to listen.","type":"Generic","is_unsent":false},{"sender_name":"Bilal Hasson","timestamp_ms":1607299433381,"content":"It is, I agree.","type":"Generic","is_unsent":false},{"sender_name":"Genevieve Hasson","timestamp_ms":1607299411819,"content":"I never push you to talk about your experience","type":"Generic","is_unsent":false},{"sender_name":"Genevieve Hasson","timestamp_ms":1607299393333,"content":"It easier to be accepting of others than yourself","type":"Generic","is_unsent":false},{"sender_name":"Bilal Hasson","timestamp_ms":1607299363305,"content":"There you go, so you know how I feel 🥰","type":"Generic","is_unsent":false},{"sender_name":"Genevieve Hasson","timestamp_ms":1607299349700,"content":"It would not","type":"Generic","is_unsent":false},{"sender_name":"Genevieve Hasson","timestamp_ms":1607299342858,"content":"No","type":"Generic","is_unsent":false},{"sender_name":"Bilal Hasson","timestamp_ms":1607299329525,"content":"Do you think if I told you it happened to me, would your opinion of me change?","type":"Generic","is_unsent":false},{"sender_name":"Genevieve Hasson","timestamp_ms":1607299328757,"content":"Reacted ❤️ to your message","type":"Generic","is_unsent":false},{"sender_name":"Genevieve Hasson","timestamp_ms":1607299327849,"content":"Reacted ❤️ to your message","type":"Generic","is_unsent":false},{"sender_name":"Genevieve Hasson","timestamp_ms":1607299324550,"content":"💙","type":"Generic","is_unsent":false},{"sender_name":"Bilal Hasson","timestamp_ms":1607299292796,"content":"Nothing could ever!","reactions":[{"reaction":"❤️","actor":"Genevieve Hasson"},{"reaction":"❤️","actor":"Genevieve Hasson"}],"type":"Generic","is_unsent":false},{"sender_name":"Bilal Hasson","timestamp_ms":1607299288241,"content":"I think you will one day 💚 nope!","reactions":[{"reaction":"❤️","actor":"Genevieve Hasson"},{"reaction":"❤️","actor":"Genevieve Hasson"}],"type":"Generic","is_unsent":false},{"sender_name":"Genevieve Hasson","timestamp_ms":1607299263246,"content":"If you knew all of this from day one would it have changed your mind?","type":"Generic","is_unsent":false},{"sender_name":"Genevieve Hasson","timestamp_ms":1607299231625,"content":"I wish I saw myself like you do","type":"Generic","is_unsent":false},{"sender_name":"Genevieve Hasson","timestamp_ms":1607299218984,"content":"Reacted ❤️ to your message","type":"Generic","is_unsent":false}]